MANIFEST.in
README.rst
setup.py
bin/clifig
clifig/__init__.py
clifig.egg-info/PKG-INFO
clifig.egg-info/SOURCES.txt
clifig.egg-info/dependency_links.txt
clifig.egg-info/top_level.txt