Metadata-Version: 1.1
Name: clifig
Version: 0.1
Summary: A simple prompt to modify config files.
Home-page: https://github.com/andrewguenther/clifig
Author: Andrew Guenther
Author-email: guenther.andrew.j@gmail.com
License: MIT
Keywords: ConfigParser command-line cli config configuration conf
Platform: UNKNOWN
Classifier: License :: OSI Approved :: MIT License
Classifier: Development Status :: 3 - Alpha
Classifier: Operating System :: OS Independent
Classifier: Topic :: Utilities
